bare/__init__.py
bare/__main__.py
bare/ast.py
bare/bare_ast.py
bare/dump.py
bare/lex.py
bare/parser.py
bare/schema.py
bare/test___init__.py
bare/test_aggregates.py
bare/test_lexer.py
bare/test_parser.py
bare/test_primitives.py
bare/test_varint.py
bare-0.7.0.dist-info/DESCRIPTION.rst
bare-0.7.0.dist-info/METADATA
bare-0.7.0.dist-info/RECORD
bare-0.7.0.dist-info/WHEEL
bare-0.7.0.dist-info/entry_points.txt
bare-0.7.0.dist-info/metadata.json
bare-0.7.0.dist-info/top_level.txt
